tests
torch_embed_sim
