Metadata-Version: 2.1
Name: torch-embed-sim
Version: 0.3.1
Summary: Embedding similarity implemented in PyTorch
Home-page: https://github.com/CyberZHG/torch-embed-sim
Author: CyberZHG
Author-email: CyberZHG@gmail.com
License: MIT
Platform: UNKNOWN
Classifier: Programming Language :: Python :: 2.7
Classifier: Programming Language :: Python :: 3.6
Classifier: License :: OSI Approved :: MIT License
Classifier: Operating System :: OS Independent
